{"stat.useItem.minecraft.command_block":3,"stat.walkOneCm":41488,"achievement.openInventory":13,"stat.useItem.minecraft.stone":14,"stat.useItem.minecraft.repeater":2,"stat.useItem.minecraft.flint_and_steel":9,"stat.leaveGame":1,"stat.useItem.minecraft.wooden_button":1,"stat.damageTaken":490,"stat.useItem.minecraft.lava_bucket":18,"stat.useItem.minecraft.bucket":30,"stat.flyOneCm":25588,"stat.deaths":2,"stat.drop":2,"stat.jump":256,"stat.swimOneCm":1651,"stat.playOneMinute":36256,"stat.useItem.minecraft.redstone_block":64,"stat.fallOneCm":1113,"stat.useItem.minecraft.redstone":5,"stat.damageDealt":10,"stat.crouchOneCm":1355,"stat.timeSinceDeath":22540,"stat.useItem.minecraft.obsidian":92,"stat.useItem.minecraft.dirt":116,"stat.sprintOneCm":17907,"stat.mineBlock.minecraft.dirt":25,"stat.useItem.minecraft.redstone_ore":1,"achievement.exploreAllBiomes":{"value":0,"progress":["Plains","Hell"]},"stat.diveOneCm":90,"stat.useItem.minecraft.water_bucket":13}